awsui/__init__.py
awsui/app.py
awsui/autocomplete.py
awsui/aws_cli.py
awsui/cheatsheet.py
awsui/command_parser.py
awsui/config.py
awsui/i18n.py
awsui/logging.py
awsui/models.py
awsui/parameter_metadata.py
awsui/q_assistant.py
awsui/resource_suggester.py
awsui/service_model_loader.py
awsui-0.1.1.dist-info/METADATA
awsui-0.1.1.dist-info/WHEEL
awsui-0.1.1.dist-info/entry_points.txt
awsui-0.1.1.dist-info/licenses/LICENSE
awsui-0.1.1.dist-info/RECORD
