Metadata-Version: 2.4
Name: awsui
Version: 0.1.1
Summary: AWS Profile/SSO switching TUI built with Textual and uv
Project-URL: Homepage, https://github.com/junminhong/awsui
Project-URL: Repository, https://github.com/junminhong/awsui
Project-URL: Bug Tracker, https://github.com/junminhong/awsui/issues
Author: junminhong (jasper)
License: MIT
License-File: LICENSE
Keywords: aws,cli,profile,sso,textual,tui
Classifier: Development Status :: 4 - Beta
Classifier: Environment :: Console
Classifier: Intended Audience :: Developers
Classifier: Intended Audience :: System Administrators
Classifier: License :: OSI Approved :: MIT License
Classifier: Operating System :: OS Independent
Classifier: Programming Language :: Python :: 3
Classifier: Programming Language :: Python :: 3.13
Classifier: Topic :: System :: Systems Administration
Classifier: Topic :: Utilities
Requires-Python: <3.14,>=3.13
Requires-Dist: textual>=6.1.0
